redis_cache/__init__.py
redis_cache/rediscache.py
redis_cache/test_rediscache.py
redis_simple_cache_py3-0.0.7.dist-info/LICENSE
redis_simple_cache_py3-0.0.7.dist-info/WHEEL
redis_simple_cache_py3-0.0.7.dist-info/METADATA
redis_simple_cache_py3-0.0.7.dist-info/RECORD
